django_xmlrpc/__init__.py
django_xmlrpc/apps.py
django_xmlrpc/decorators.py
django_xmlrpc/dispatcher.py
django_xmlrpc/registry.py
django_xmlrpc/views.py
django_xmlrpc/locale/fr/LC_MESSAGES/django.mo
django_xmlrpc/locale/fr/LC_MESSAGES/django.po
django_xmlrpc/templates/xmlrpc_get.html
django_xmlrpc-0.1.8.dist-info/DESCRIPTION.rst
django_xmlrpc-0.1.8.dist-info/METADATA
django_xmlrpc-0.1.8.dist-info/RECORD
django_xmlrpc-0.1.8.dist-info/WHEEL
django_xmlrpc-0.1.8.dist-info/metadata.json
django_xmlrpc-0.1.8.dist-info/top_level.txt
