Metadata-Version: 1.1
Name: django-xmlrpc
Version: 0.1.8
Summary: XML-RPC Server App for the Django framework.
Home-page: https://github.com/Fantomas42/django-xmlrpc
Author: Fantomas42
Author-email: fantomas42@gmail.com
License: New BSD License
Keywords: django,service,xmlrpc
Platform: UNKNOWN
Classifier: Framework :: Django
Classifier: Development Status :: 5 - Production/Stable
Classifier: Environment :: Web Environment
Classifier: Programming Language :: Python
Classifier: Programming Language :: Python :: 3
Classifier: Intended Audience :: Developers
Classifier: Operating System :: OS Independent
Classifier: Topic :: Software Development :: Libraries :: Python Modules
